LICENSE.md
README.md
setup.py
drf_access_policy.egg-info/PKG-INFO
drf_access_policy.egg-info/SOURCES.txt
drf_access_policy.egg-info/dependency_links.txt
drf_access_policy.egg-info/requires.txt
drf_access_policy.egg-info/top_level.txt
rest_access_policy/__init__.py
rest_access_policy/access_policy.py
rest_access_policy/access_view_set_mixin.py
rest_access_policy/exceptions.py
rest_access_policy/field_access_mixin.py
rest_access_policy/fields.py
rest_access_policy/parsing.py
rest_access_policy/py.typed