Metadata-Version: 2.1
Name: drf-access-policy
Version: 1.4.0
Summary: Declarative access policies/permissions modeled after AWS' IAM policies.
Home-page: https://github.com/rsinger86/drf-access-policy
Author: Robert Singer
Author-email: robertgsinger@gmail.com
License: MIT
Keywords: django restframework drf access policy authorization declaritive
Platform: UNKNOWN
Classifier: License :: OSI Approved :: MIT License
Classifier: Framework :: Django
Classifier: Framework :: Django :: 2.0
Classifier: Framework :: Django :: 3.0
Classifier: Framework :: Django :: 3.1
Classifier: Framework :: Django :: 3.2
Classifier: Programming Language :: Python :: 3.5
Classifier: Programming Language :: Python :: 3.6
Classifier: Programming Language :: Python :: 3.7
Classifier: Programming Language :: Python :: 3.8
Classifier: Programming Language :: Python :: 3.9
License-File: LICENSE.md
